odoo8_addon_l10n_ch_account_statement_base_import-8.0.1.0.2.99.dev1-nspkg.pth
odoo_addons/l10n_ch_account_statement_base_import/README.rst
odoo_addons/l10n_ch_account_statement_base_import/__init__.py
odoo_addons/l10n_ch_account_statement_base_import/__openerp__.py
odoo_addons/l10n_ch_account_statement_base_import/data/UBS_export.csv
odoo_addons/l10n_ch_account_statement_base_import/data/aus_dd_esr.g11
odoo_addons/l10n_ch_account_statement_base_import/data/postfinance_xml.tar.gz
odoo_addons/l10n_ch_account_statement_base_import/data/raiffeisen_details.csv
odoo_addons/l10n_ch_account_statement_base_import/data/vesr.V11
odoo_addons/l10n_ch_account_statement_base_import/i18n/ca_ES.po
odoo_addons/l10n_ch_account_statement_base_import/i18n/de.po
odoo_addons/l10n_ch_account_statement_base_import/i18n/el_GR.po
odoo_addons/l10n_ch_account_statement_base_import/i18n/es.po
odoo_addons/l10n_ch_account_statement_base_import/i18n/fi.po
odoo_addons/l10n_ch_account_statement_base_import/i18n/fr.po
odoo_addons/l10n_ch_account_statement_base_import/i18n/fr_CH.po
odoo_addons/l10n_ch_account_statement_base_import/i18n/gl.po
odoo_addons/l10n_ch_account_statement_base_import/i18n/it.po
odoo_addons/l10n_ch_account_statement_base_import/i18n/l10n_ch_account_statement_base_import.pot
odoo_addons/l10n_ch_account_statement_base_import/i18n/nl_NL.po
odoo_addons/l10n_ch_account_statement_base_import/i18n/sl.po
odoo_addons/l10n_ch_account_statement_base_import/i18n/tr.po
odoo_addons/l10n_ch_account_statement_base_import/models/__init__.py
odoo_addons/l10n_ch_account_statement_base_import/models/account_bank_statement_import.py
odoo_addons/l10n_ch_account_statement_base_import/parsers/__init__.py
odoo_addons/l10n_ch_account_statement_base_import/parsers/base_parser.py
odoo_addons/l10n_ch_account_statement_base_import/parsers/camt.py
odoo_addons/l10n_ch_account_statement_base_import/parsers/g11_file_parser.py
odoo_addons/l10n_ch_account_statement_base_import/parsers/postfinance_file_parser.py
odoo8_addon_l10n_ch_account_statement_base_import-8.0.1.0.2.99.dev1.dist-info/METADATA
odoo8_addon_l10n_ch_account_statement_base_import-8.0.1.0.2.99.dev1.dist-info/WHEEL
odoo8_addon_l10n_ch_account_statement_base_import-8.0.1.0.2.99.dev1.dist-info/namespace_packages.txt
odoo8_addon_l10n_ch_account_statement_base_import-8.0.1.0.2.99.dev1.dist-info/top_level.txt
odoo8_addon_l10n_ch_account_statement_base_import-8.0.1.0.2.99.dev1.dist-info/RECORD
