Metadata-Version: 2.1
Name: odoo8-addon-l10n-ch-account-statement-base-import
Version: 8.0.1.0.2.99.dev1
Summary: Swiss bank statements import
Home-page: http://www.compassion.ch/
Author: Compassion CH, Camptocamp, Odoo Community Association (OCA)
Author-email: support@odoo-community.org
License: AGPL-3
Platform: UNKNOWN
Classifier: Programming Language :: Python
Classifier: Framework :: Odoo
Classifier: License :: OSI Approved :: GNU Affero General Public License v3
Requires-Python: ~=2.7
Requires-Dist: odoo8-addon-account-bank-statement-import-camt
Requires-Dist: odoo (<9.0a,>=8.0a)
Requires-Dist: wand
Requires-Dist: xlrd
